Metadata-Version: 2.4
Name: mseep-mcp-finnhub
Version: 0.1.4
Summary: An MCP server to connect with Finnhub financial API.
Author-email: mseep <support@skydeck.ai>
Project-URL: Home, https://github.com/catherinedparnell/mcp-finnhub
Requires-Python: >=3.13
Requires-Dist: mcp>=1.0.0
Requires-Dist: python-dotenv>=1.0.1
Requires-Dist: fastmcp>=0.4.0
Requires-Dist: finnhub-python
